yboss/yboss.py
yboss/__init__.py
yboss-0.1.1.dist-info/RECORD
yboss-0.1.1.dist-info/DESCRIPTION.rst
yboss-0.1.1.dist-info/top_level.txt
yboss-0.1.1.dist-info/WHEEL
yboss-0.1.1.dist-info/METADATA
yboss-0.1.1.dist-info/pydist.json
