Metadata-Version: 2.0
Name: yboss
Version: 0.1.1
Summary: Python wrapper for Yahoo Boss API
Home-page: https://github.com/inovatho/yboss
Author: Inovatho
Author-email: inovacao@catho.com
License: BSD
Keywords: yboss
Platform: UNKNOWN
Classifier: Development Status :: 2 - Pre-Alpha
Classifier: Intended Audience :: Developers
Classifier: License :: OSI Approved :: BSD License
Classifier: Natural Language :: English
Classifier: Programming Language :: Python :: 2
Classifier: Programming Language :: Python :: 2.6
Classifier: Programming Language :: Python :: 2.7
Classifier: Programming Language :: Python :: 3
Classifier: Programming Language :: Python :: 3.3
Requires-Dist: requests
Requires-Dist: oauthlib
